{
    "metadata": {
        "title": "☒ Approach",
        "citation": "☒ Approach",
        "jurisdiction": "Ontario",
        "last_updated": "2025-03-09",
        "source_url": "https://www.fsrao.ca/media/15261/download"
    },
    "structure": [
        {
            "id": "section_1",
            "type": "section",
            "number": "1",
            "title": " ",
            "citation_path": "s. 1",
            "content": [
                {
                    "id": "section_1_text_0",
                    "type": "paragraph",
                    "text": " 1 ",
                    "citation_path": "s. 1"
                },
                {
                    "id": "section_1_text_1",
                    "type": "paragraph",
                    "text": "  Guidance  ",
                    "citation_path": "s. 1"
                },
                {
                    "id": "section_1_text_2",
                    "type": "paragraph",
                    "text": "☒   Interpretation ",
                    "citation_path": "s. 1"
                },
                {
                    "id": "section_1_text_3",
                    "type": "paragraph",
                    "text": "☒  Approach ",
                    "citation_path": "s. 1"
                },
                {
                    "id": "section_1_text_4",
                    "type": "paragraph",
                    "text": "☐    Information ",
                    "citation_path": "s. 1"
                },
                {
                    "id": "section_1_text_5",
                    "type": "paragraph",
                    "text": "☐   Decision ",
                    "citation_path": "s. 1"
                },
                {
                    "id": "section_1_text_6",
                    "type": "paragraph",
                    "text": "GUI APP AU013 6APP  | 12.12.22 ",
                    "citation_path": "s. 1"
                },
                {
                    "id": "section_1_text_7",
                    "type": "paragraph",
                    "text": "Effective Date: December 12, 2022 ",
                    "citation_path": "s. 1"
                },
                {
                    "id": "section_1_text_8",
                    "type": "paragraph",
                    "text": "Identifier: No. AU0136APP ",
                    "citation_path": "s. 1"
                },
                {
                    "id": "section_1_text_9",
                    "type": "paragraph",
                    "text": "Reporting and resolution of rating and ",
                    "citation_path": "s. 1"
                },
                {
                    "id": "section_1_text_10",
                    "type": "paragraph",
                    "text": "underwriting errors ",
                    "citation_path": "s. 1"
                },
                {
                    "id": "section_1_text_11",
                    "type": "paragraph",
                    "text": "Purpose and scope ",
                    "citation_path": "s. 1"
                },
                {
                    "id": "section_1_text_12",
                    "type": "paragraph",
                    "text": "This Approach and Interpretation Guidance (“Guidance”) sets out regulatory requirements and ",
                    "citation_path": "s. 1"
                },
                {
                    "id": "section_1_text_13",
                    "type": "paragraph",
                    "text": "the Financial Services Regulatory Authority of Ontario’s[1] (“FSRA”) compliance expectations, ",
                    "citation_path": "s. 1"
                },
                {
                    "id": "section_1_text_14",
                    "type": "paragraph",
                    "text": "principles, processes, and practices to all insurers offering automobile insurance[2] in Ontario ",
                    "citation_path": "s. 1"
                },
                {
                    "id": "section_1_text_15",
                    "type": "paragraph",
                    "text": "(collectively referred to as “insurers”) regarding the regulatory reporting and resolution of rating and underwriting errors.",
                    "citation_path": "s. 1"
                },
                {
                    "id": "section_1_text_16",
                    "type": "paragraph",
                    "text": "Rationale and background ",
                    "citation_path": "s. 1"
                },
                {
                    "id": "section_1_text_17",
                    "type": "paragraph",
                    "text": "The objective of this Guidance is to ensure that: ",
                    "citation_path": "s. 1"
                },
                {
                    "id": "section_1_text_18",
                    "type": "paragraph",
                    "text": "1. insurers are aware of FSRA’s processes and expectations when an automobile insurance rating or underwriting error occurs, and reporting is consistent across the sector ",
                    "citation_path": "s. 1"
                },
                {
                    "id": "section_1_text_19",
                    "type": "paragraph",
                    "text": "2. insurers treat consumers fairly in the resolution of rating and underwriting errors[3]. ",
                    "citation_path": "s. 1"
                },
                {
                    "id": "section_1_text_20",
                    "type": "paragraph",
                    "text": " 2 Guidance  ",
                    "citation_path": "s. 1"
                },
                {
                    "id": "section_1_text_21",
                    "type": "paragraph",
                    "text": "GUI APP AU013 6APP | 12.12 .22 ",
                    "citation_path": "s. 1"
                },
                {
                    "id": "section_1_text_22",
                    "type": "paragraph",
                    "text": "Rating errors ",
                    "citation_path": "s. 1"
                },
                {
                    "id": "section_1_text_23",
                    "type": "paragraph",
                    "text": "A rating error occurs when an insurer charges a consumer a rate other than the approved rate as filed with FSRA pursuant to the: ",
                    "citation_path": "s. 1"
                },
                {
                    "id": "section_1_text_24",
                    "type": "paragraph",
                    "text": "1. Automobile Insurance Rate Stabilization Act (“AIRSA”) for the Private Passenger Automobile (“PPA”) category ",
                    "citation_path": "s. 1"
                },
                {
                    "id": "section_1_text_25",
                    "type": "paragraph",
                    "text": "2. Insurance Act (the “Act”) for the other than PPA categories[4] ",
                    "citation_path": "s. 1"
                },
                {
                    "id": "section_1_text_26",
                    "type": "paragraph",
                    "text": "A rating error also occurs when an insurer implements processes or procedures that result in the incorrect classification of a consumer and thereby impacts their rating or ability to purchase insurance. ",
                    "citation_path": "s. 1"
                },
                {
                    "id": "section_1_text_27",
                    "type": "paragraph",
                    "text": "Underwriting errors ",
                    "citation_path": "s. 1"
                },
                {
                    "id": "section_1_text_28",
                    "type": "paragraph",
                    "text": "An underwriting error occurs when an insurer uses reasons other than the approved reasons as filed under s. 238 of the Act",
                    "citation_path": "s. 1"
                },
                {
                    "id": "section_1_text_29",
                    "type": "paragraph",
                    "text": "[5] to: ",
                    "citation_path": "s. 1"
                },
                {
                    "id": "section_1_text_30",
                    "type": "paragraph",
                    "text": "1. decline to issue, terminate, or refuse to renew a contract[6] ",
                    "citation_path": "s. 1"
                },
                {
                    "id": "section_1_text_31",
                    "type": "paragraph",
                    "text": "2. refuse to provide or continue a coverage or endorsement ",
                    "citation_path": "s. 1"
                },
                {
                    "id": "section_1_text_32",
                    "type": "section",
                    "text": "An underwriting error also occurs when an insurer implements formal or informal processes and procedures, whether intentionally or unintentionally, that make it more difficult for consumers to interact with the insurer, its appointed broker(s) or its Agent(s) and thereby discourage or delay consumers from applying for, renewing, or otherwise obtaining automobile insurance.",
                    "citation_path": "s. 1"
                },
                {
                    "id": "section_1_text_33",
                    "type": "paragraph",
                    "text": "[7] ",
                    "citation_path": "s. 1"
                },
                {
                    "id": "section_1_text_34",
                    "type": "paragraph",
                    "text": "Need for Guidance on reporting and resolution of errors ",
                    "citation_path": "s. 1"
                },
                {
                    "id": "section_1_text_35",
                    "type": "section",
                    "text": "FSRA does not currently have guidance establishing its view on the reporting and resolution of rating and underwriting errors. The reporting of such errors remains inconsistent across the automobile insurance sector and there is a lack of transparency regarding how FSRA will address circumstances where an unreported error is discovered through alternative means (e.g., while reviewing a consumer complaint or reviewing an insurer’s rate or underwriting rules filing). ",
                    "citation_path": "s. 1"
                },
                {
                    "id": "section_1_text_36",
                    "type": "paragraph",
                    "text": " 3 Guidance  ",
                    "citation_path": "s. 1"
                },
                {
                    "id": "section_1_text_37",
                    "type": "paragraph",
                    "text": "GUI APP AU013 6APP | 12.12 .22 ",
                    "citation_path": "s. 1"
                },
                {
                    "id": "section_1_text_38",
                    "type": "paragraph",
                    "text": "Further, there is no express requirement in the Act or AIRSA regarding the reporting of rating and underwriting errors to FSRA or how such errors are to be resolved. ",
                    "citation_path": "s. 1"
                },
                {
                    "id": "section_1_text_39",
                    "type": "paragraph",
                    "text": "Interpretation - Regulatory requirements ",
                    "citation_path": "s. 1"
                },
                {
                    "id": "section_1_text_40",
                    "type": "paragraph",
                    "text": "Rating errors ",
                    "citation_path": "s. 1"
                },
                {
                    "id": "section_1_text_41",
                    "type": "paragraph",
                    "text": "FSRA is interpreting the following subsections of the Act as requiring insurers to report and resolve rating errors: ",
                    "citation_path": "s. 1"
                },
                {
                    "id": "section_1_text_42",
                    "type": "section",
                    "text": "• In relation to automobile insurance for the other than the PPA categories, s. 417(1) and s. 417(2) of the Act prohibit insurers from using a risk classification system or rate that has not been approved by FSRA. Given that a rating error is prohibited by the Act, as such an error constitutes using a risk classification system or rate not approved by FSRA, FSRA views the word “approved” according to this Guidance as requiring insurers to report and resolve rating errors for the non-PPA categories of automobile insurance. ",
                    "citation_path": "s. 1"
                },
                {
                    "id": "section_1_text_43",
                    "type": "section",
                    "text": "• In relation to the PPA category of automobile insurance, s. 8 of AIRSA prohibits insurers from charging a rate other than the authorized rate. Given that a rating error is prohibited by AIRSA, as such an error constitutes using a non-authorized rate, FSRA views the word “authorized” in this Guidance as requiring insurers to report and resolve errors for the PPA category of automobile insurance. ",
                    "citation_path": "s. 1"
                },
                {
                    "id": "section_1_text_44",
                    "type": "section",
                    "text": "• Paragraph (3) of s. 442.3(1) of the Act requires insurers in the context of an inquiry to provide FSRA with information about their activities related to the business of insurance. It is FSRA’s position that the phrase “information about the activities related to the business of insurance” includes the reporting and resolution of rating errors by insurers for all categories of automobile insurance. ",
                    "citation_path": "s. 1"
                },
                {
                    "id": "section_1_text_45",
                    "type": "section",
                    "text": "• S. 3(1)(f) of the Financial Services Regulatory Authority of Ontario Act (the “FSRA Act”) states that an object of FSRA is to promote transparency and the disclosure of information by the insurance sector. FSRA’s interpretation of the requirements of the Act and AIRSA, as noted above, is consistent with the position that the reporting and resolution of rating errors for all categories of automobile insurance promotes transparency and the disclosure of information by insurers. ",
                    "citation_path": "s. 1"
                },
                {
                    "id": "section_1_text_46",
                    "type": "paragraph",
                    "text": " 4 Guidance  ",
                    "citation_path": "s. 1"
                },
                {
                    "id": "section_1_text_47",
                    "type": "paragraph",
                    "text": "GUI APP AU013 6APP | 12.12 .22 ",
                    "citation_path": "s. 1"
                },
                {
                    "id": "section_1_text_48",
                    "type": "section",
                    "text": "• S. 9(1)(v) of the Unfair or Deceptive Acts or Practices Rule (the “UDAP Rule”) prescribes as an unfair or deceptive act or practice any conduct, including inaction or omission, which results in or could reasonably be expected to result in unfair treatment by an insurer, agent or broker to a consumer with regard to any matter relating to the issuance of contracts of automobile insurance or renewals of existing contracts of automobile insurance, including but not limited to, misclassifying a person or vehicle under the risk classification system used by an insurer or that an insurer is legally required to use. ",
                    "citation_path": "s. 1"
                },
                {
                    "id": "section_1_text_49",
                    "type": "section",
                    "text": "• S. 3(1) of the UDAP Rule prescribes as an unfair or deceptive act or practice any conduct, including inaction or omission, which results in or could reasonably be expected to result in the commission of any act prohibited under the Act, or under any regulation or FSRA rule made under the Act, including ss. 417(1) and 417(2) of the Act ",
                    "citation_path": "s. 1"
                },
                {
                    "id": "section_1_text_50",
                    "type": "section",
                    "text": "• FSRA’s position is that a failure by an insurer to report and resolve rating errors constitutes conduct which would reasonably be expected to result in the outcomes described in s. 3(1) and s. 9(1)(v) of the UDAP Rule (as mentioned above) and accordingly, FSRA may take action pursuant to s. 439 of the Act ",
                    "citation_path": "s. 1"
                },
                {
                    "id": "section_1_text_51",
                    "type": "paragraph",
                    "text": "Underwriting errors ",
                    "citation_path": "s. 1"
                },
                {
                    "id": "section_1_text_52",
                    "type": "paragraph",
                    "text": "FSRA is interpreting the following subsections of the Act as requiring insurers to report and resolve underwriting errors: ",
                    "citation_path": "s. 1"
                },
                {
                    "id": "section_1_text_53",
                    "type": "section",
                    "text": "• S. 238(1) of the Act prohibits, with respect to automobile insurance, an insurer from declining to issue, terminating or refusing to renew a contract or refusing to provide or continue a coverage endorsement except on a ground filed with FSRA. FSRA regards the phrase “decline to issue, terminate or refuse to renew…except on a filed ground,” as requiring insurers to report and resolve an underwriting error to FSRA where such an error is based on a non-filed ground. ",
                    "citation_path": "s. 1"
                },
                {
                    "id": "section_1_text_54",
                    "type": "section",
                    "text": "• Paragraph (3) of s. 442.3(1) of the Act requires insurers in the context of an inquiry to provide FSRA with information about their activities related to the business of insurance. It is FSRA’s position that the phrase “information about the activities related to the business of insurance” as including the reporting and resolution of underwriting errors by insurers. ",
                    "citation_path": "s. 1"
                },
                {
                    "id": "section_1_text_55",
                    "type": "paragraph",
                    "text": "5 Guidance  ",
                    "citation_path": "s. 1"
                },
                {
                    "id": "section_1_text_56",
                    "type": "paragraph",
                    "text": "GUI APP AU013 6APP | 12.12 .22 ",
                    "citation_path": "s. 1"
                },
                {
                    "id": "section_1_text_57",
                    "type": "paragraph",
                    "text": "•S. 3(1)(f) of the FSRA Act  states that an object of FSRA is to promote transparency and",
                    "citation_path": "s. 1"
                },
                {
                    "id": "section_1_text_58",
                    "type": "paragraph",
                    "text": "the disclosure of information by the insurance sector. FSRA’s interpretation of the",
                    "citation_path": "s. 1"
                },
                {
                    "id": "section_1_text_59",
                    "type": "paragraph",
                    "text": "requirements of the Act  as noted above, is consistent with the position that the reporting",
                    "citation_path": "s. 1"
                },
                {
                    "id": "section_1_text_60",
                    "type": "paragraph",
                    "text": "and resolution of underwriting errors promotes transparency and the disclosure ofinformation by insurers.",
                    "citation_path": "s. 1"
                },
                {
                    "id": "section_1_text_61",
                    "type": "paragraph",
                    "text": "•S. 9(1)(i) of  the UDAP Rule prescribes as an unfair or deceptive act or practice any",
                    "citation_path": "s. 1"
                },
                {
                    "id": "section_1_text_62",
                    "type": "paragraph",
                    "text": "conduct, including inaction or omission, which results in or could reasonably be expectedto result in unfair treatment by an insurer, agent or broker to a consumer with regard toany matter relating to the issuance of contracts of automobile insurance or renewals of",
                    "citation_path": "s. 1"
                },
                {
                    "id": "section_1_text_63",
                    "type": "section",
                    "text": "existing contracts of automobile insurance, including but not limited to, variance of formalor informal processes and procedures which make it more difficult for certain persons tointeract with an insurer, broker or agent for the purpose of discouraging or delaying suchpersons from applying for, renewing or obtaining automobile insurance",
                    "citation_path": "s. 1"
                },
                {
                    "id": "section_1_text_64",
                    "type": "section",
                    "text": "•S. 3(2) of the UDAP Rule prescribes as an unfair or deceptive act or practice any conduct,including inaction or omission, which results in or could reasonably be expected to resultin any provision of the Act, or a regulation or FSRA rule made under the Act, not beingcomplied with resulting in the unfair treatment or unfair discrimination of a person",
                    "citation_path": "s. 1"
                },
                {
                    "id": "section_1_text_65",
                    "type": "section",
                    "text": "•FSRA’s position is that a failure by an insurer to report and resolve underwriting errorsconstitutes conduct which would reasonably be expected to result in the outcomesdescribed in s. 3(2) and s. 9(1)(i) of the UDAP Rule (as mentioned above) andaccordingly, FSRA may take action pursuant to s. 439 of the Act",
                    "citation_path": "s. 1"
                },
                {
                    "id": "section_1_text_66",
                    "type": "paragraph",
                    "text": "Consequences of the failure to report, or, if applicable, resolve errors  ",
                    "citation_path": "s. 1"
                },
                {
                    "id": "section_1_text_67",
                    "type": "paragraph",
                    "text": "FSRA has the authority to impose an administrative monetary penalty on, or lay provincial offence charges against, an insurer who has committed a rating or underwriting error.",
                    "citation_path": "s. 1"
                },
                {
                    "id": "section_1_text_68",
                    "type": "paragraph",
                    "text": "[8] FSRA ",
                    "citation_path": "s. 1"
                },
                {
                    "id": "section_1_text_69",
                    "type": "paragraph",
                    "text": "also has the authority to impose an Order or seek a court order which requires the insurer to cease action, take action, or to suspend the insurer’s license under the Act, without prior notice.",
                    "citation_path": "s. 1"
                },
                {
                    "id": "section_1_text_70",
                    "type": "paragraph",
                    "text": "[9] ",
                    "citation_path": "s. 1"
                },
                {
                    "id": "section_1_text_71",
                    "type": "section",
                    "text": "In general, insurers are responsible for ensuring that they have appropriate controls in place to identify and correct rating and underwriting errors and ensure the fair treatment of consumers related thereto. FSRA will consider this overriding obligation as critical to its Enforcement response where an insurer has failed to report such errors or adequately resolve them. ",
                    "citation_path": "s. 1"
                },
                {
                    "id": "section_1_text_72",
                    "type": "paragraph",
                    "text": "6 Guidance  ",
                    "citation_path": "s. 1"
                },
                {
                    "id": "section_1_text_73",
                    "type": "paragraph",
                    "text": "GUI APP AU013 6APP | 12.12 .22 ",
                    "citation_path": "s. 1"
                },
                {
                    "id": "section_1_text_74",
                    "type": "paragraph",
                    "text": "FSRA considers insurers’ compliance, or lack thereof, with this Guidance as one of several ",
                    "citation_path": "s. 1"
                },
                {
                    "id": "section_1_text_75",
                    "type": "paragraph",
                    "text": "factors in determining FSRA’s Enforcement response to a rating or underwriting error. ",
                    "citation_path": "s. 1"
                },
                {
                    "id": "section_1_text_76",
                    "type": "paragraph",
                    "text": "Principles  ",
                    "citation_path": "s. 1"
                },
                {
                    "id": "section_1_text_77",
                    "type": "paragraph",
                    "text": "FSRA’s Rate Regulation Principles[10] (“RRP”) are foundational to FSRA’s approach to ",
                    "citation_path": "s. 1"
                },
                {
                    "id": "section_1_text_78",
                    "type": "paragraph",
                    "text": "automobile insurance rate regulation. In developing a framework for the handling of automobile insurance rating and underwriting errors, FSRA was guided by the RRP’s principles of Consumer Focus and Transparency and Disclosure. ",
                    "citation_path": "s. 1"
                },
                {
                    "id": "section_1_text_79",
                    "type": "paragraph",
                    "text": "In supervising and regulating the insurance sector, FSRA is required to administer and enforce the Act and its regulations in a manner consistent with FSRA’s statutory objects.",
                    "citation_path": "s. 1"
                },
                {
                    "id": "section_1_text_80",
                    "type": "paragraph",
                    "text": "[11] ",
                    "citation_path": "s. 1"
                },
                {
                    "id": "section_1_text_81",
                    "type": "paragraph",
                    "text": "Approach – Supervision, processes, and practices  ",
                    "citation_path": "s. 1"
                },
                {
                    "id": "section_1_text_82",
                    "type": "paragraph",
                    "text": "Reporting and resolution of errors  ",
                    "citation_path": "s. 1"
                },
                {
                    "id": "section_1_text_83",
                    "type": "paragraph",
                    "text": "Insurers are expected to report all rating and underwriting errors to FSRA in writing. Please see the table below for error types and how they should be reported. In advance of reporting rating or underwriting errors, insurers may contact their FSRA analyst for assistance. ",
                    "citation_path": "s. 1"
                },
                {
                    "id": "section_1_text_84",
                    "type": "paragraph",
                    "text": "Type of Error ",
                    "citation_path": "s. 1"
                },
                {
                    "id": "section_1_text_85",
                    "type": "paragraph",
                    "text": "Description Timelines  ",
                    "citation_path": "s. 1"
                },
                {
                    "id": "section_1_text_86",
                    "type": "paragraph",
                    "text": "Major Rating Error Threshold:",
                    "citation_path": "s. 1"
                },
                {
                    "id": "section_1_text_87",
                    "type": "paragraph",
                    "text": " A rating error is Major if, ",
                    "citation_path": "s. 1"
                },
                {
                    "id": "section_1_text_88",
                    "type": "paragraph",
                    "text": "•the sum of the absolute value of premium overcharges  ",
                    "citation_path": "s. 1"
                },
                {
                    "id": "section_1_text_89",
                    "type": "paragraph",
                    "text": "and premium undercharges resulting from the r ating error  ",
                    "citation_path": "s. 1"
                },
                {
                    "id": "section_1_text_90",
                    "type": "paragraph",
                    "text": "exceeds the gr eater of $5000 or 0.02% of the insurer’s ",
                    "citation_path": "s. 1"
                },
                {
                    "id": "section_1_text_91",
                    "type": "paragraph",
                    "text": "total written premiums[12] for the category affected[13]",
                    "citation_path": "s. 1"
                },
                {
                    "id": "section_1_text_92",
                    "type": "paragraph",
                    "text": "andReported within 30 business days from the time the rating and/or underwriting error is confirmed.",
                    "citation_path": "s. 1"
                },
                {
                    "id": "section_1_text_93",
                    "type": "paragraph",
                    "text": "[16] ",
                    "citation_path": "s. 1"
                },
                {
                    "id": "section_1_text_94",
                    "type": "paragraph",
                    "text": "7 Guidance  ",
                    "citation_path": "s. 1"
                },
                {
                    "id": "section_1_text_95",
                    "type": "paragraph",
                    "text": "GUI APP AU013 6APP | 12.12 .22 ",
                    "citation_path": "s. 1"
                },
                {
                    "id": "section_1_text_96",
                    "type": "paragraph",
                    "text": "Type ",
                    "citation_path": "s. 1"
                },
                {
                    "id": "section_1_text_97",
                    "type": "paragraph",
                    "text": "of ",
                    "citation_path": "s. 1"
                },
                {
                    "id": "section_1_text_98",
                    "type": "paragraph",
                    "text": "Error  Description Timelines  ",
                    "citation_path": "s. 1"
                },
                {
                    "id": "section_1_text_99",
                    "type": "paragraph",
                    "text": "•the number of written exposures impacted from",
                    "citation_path": "s. 1"
                },
                {
                    "id": "section_1_text_100",
                    "type": "paragraph",
                    "text": "overcharges and undercharges due to the rating error",
                    "citation_path": "s. 1"
                },
                {
                    "id": "section_1_text_101",
                    "type": "paragraph",
                    "text": "exceeds the greater of 100 exposures or 0.5% of the",
                    "citation_path": "s. 1"
                },
                {
                    "id": "section_1_text_102",
                    "type": "paragraph",
                    "text": "insurer’s total written exposures[14] for the category",
                    "citation_path": "s. 1"
                },
                {
                    "id": "section_1_text_103",
                    "type": "paragraph",
                    "text": "affected[15]",
                    "citation_path": "s. 1"
                },
                {
                    "id": "section_1_text_104",
                    "type": "paragraph",
                    "text": "Underwriting Error Threshold:",
                    "citation_path": "s. 1"
                },
                {
                    "id": "section_1_text_105",
                    "type": "paragraph",
                    "text": "An underwriting error is Major if, ",
                    "citation_path": "s. 1"
                },
                {
                    "id": "section_1_text_106",
                    "type": "paragraph",
                    "text": "•more than 100 exposures are affected by the underwriting",
                    "citation_path": "s. 1"
                },
                {
                    "id": "section_1_text_107",
                    "type": "paragraph",
                    "text": "error",
                    "citation_path": "s. 1"
                },
                {
                    "id": "section_1_text_108",
                    "type": "paragraph",
                    "text": "Minor  When the rating and/or underwriting error falls below the above threshol",
                    "citation_path": "s. 1"
                },
                {
                    "id": "section_1_text_109",
                    "type": "paragraph",
                    "text": "d. Reported in writ",
                    "citation_path": "s. 1"
                },
                {
                    "id": "section_1_text_110",
                    "type": "paragraph",
                    "text": "ing annually ",
                    "citation_path": "s. 1"
                },
                {
                    "id": "section_1_text_111",
                    "type": "paragraph",
                    "text": "at a date established by FSRA.  ",
                    "citation_path": "s. 1"
                },
                {
                    "id": "section_1_text_112",
                    "type": "paragraph",
                    "text": "It should be noted that FSRA may require a lower threshold for an insurer where it determines warrant",
                    "citation_path": "s. 1"
                },
                {
                    "id": "section_1_text_113",
                    "type": "paragraph",
                    "text": "ed. This could include situations where the insurer has historically shown a higher ",
                    "citation_path": "s. 1"
                },
                {
                    "id": "section_1_text_114",
                    "type": "paragraph",
                    "text": "propensity for committing rating or underwriting errors or there are concerns about the effectiveness of the insurer’s control environment as it relates to rating and underwriting errors.  ",
                    "citation_path": "s. 1"
                },
                {
                    "id": "section_1_text_115",
                    "type": "paragraph",
                    "text": "Regardless of whether the error is major or minor, insurers must remediate in favour of all consumer",
                    "citation_path": "s. 1"
                },
                {
                    "id": "section_1_text_116",
                    "type": "paragraph",
                    "text": "s affected by the error.[17] FSRA will require ad ditional information from the insurer, ",
                    "citation_path": "s. 1"
                },
                {
                    "id": "section_1_text_117",
                    "type": "paragraph",
                    "text": "including a complete description and source of the error, how it was discovered, its impact and timing, corrective measures taken to- date, and an action plan to remediate the impact on ",
                    "citation_path": "s. 1"
                },
                {
                    "id": "section_1_text_118",
                    "type": "paragraph",
                    "text": "affected consumers (“remediation  plan”)",
                    "citation_path": "s. 1"
                },
                {
                    "id": "section_1_text_119",
                    "type": "paragraph",
                    "text": ".[18] Insurers requiring more than 30 business days to ",
                    "citation_path": "s. 1"
                },
                {
                    "id": "section_1_text_120",
                    "type": "paragraph",
                    "text": "8 Guidance  ",
                    "citation_path": "s. 1"
                },
                {
                    "id": "section_1_text_121",
                    "type": "paragraph",
                    "text": "GUI APP AU013 6APP | 12.12 .22 ",
                    "citation_path": "s. 1"
                },
                {
                    "id": "section_1_text_122",
                    "type": "paragraph",
                    "text": "report the error and prepare the remediation plan should contact FSRA to discuss potential ",
                    "citation_path": "s. 1"
                },
                {
                    "id": "section_1_text_123",
                    "type": "paragraph",
                    "text": "options. ",
                    "citation_path": "s. 1"
                },
                {
                    "id": "section_1_text_124",
                    "type": "paragraph",
                    "text": "Refunds to consumers must include the amount of any premium overpayment together with interest for the period that the error was in effect. ",
                    "citation_path": "s. 1"
                },
                {
                    "id": "section_1_text_125",
                    "type": "paragraph",
                    "text": "Supervisory approach  ",
                    "citation_path": "s. 1"
                },
                {
                    "id": "section_1_text_126",
                    "type": "paragraph",
                    "text": "FSRA may formally examine an insurer’s processes and practices[19] ensuring rating and ",
                    "citation_path": "s. 1"
                },
                {
                    "id": "section_1_text_127",
                    "type": "paragraph",
                    "text": "underwriting errors are resolved, as is legally required under the Act. In deciding whether an examination is required, FSRA may consider: ",
                    "citation_path": "s. 1"
                },
                {
                    "id": "section_1_text_128",
                    "type": "paragraph",
                    "text": "1.the number of major and minor errors reported by the insurer or insurance group to FSRAi",
                    "citation_path": "s. 1"
                },
                {
                    "id": "section_1_text_129",
                    "type": "paragraph",
                    "text": "n the previous 12 months",
                    "citation_path": "s. 1"
                },
                {
                    "id": "section_1_text_130",
                    "type": "paragraph",
                    "text": "2.the insurer’s or insurer group’s history of reporting and resolving rating and underwritinge",
                    "citation_path": "s. 1"
                },
                {
                    "id": "section_1_text_131",
                    "type": "paragraph",
                    "text": "rrors",
                    "citation_path": "s. 1"
                },
                {
                    "id": "section_1_text_132",
                    "type": "paragraph",
                    "text": "3.the frequency and extent of recent rating or underwriting changes, including policym",
                    "citation_path": "s. 1"
                },
                {
                    "id": "section_1_text_133",
                    "type": "paragraph",
                    "text": "anagement system changes",
                    "citation_path": "s. 1"
                },
                {
                    "id": "section_1_text_134",
                    "type": "paragraph",
                    "text": "The above list is not exhaustive as additional factors may be identified and considered by FSRA w",
                    "citation_path": "s. 1"
                },
                {
                    "id": "section_1_text_135",
                    "type": "paragraph",
                    "text": "hich warrant a formal examination. FSRA will allocate its examination and enforcement ",
                    "citation_path": "s. 1"
                },
                {
                    "id": "section_1_text_136",
                    "type": "paragraph",
                    "text": "resources based on its assessment of the insurer’s compliance with this guidance and its approved prioritization mechanism.  ",
                    "citation_path": "s. 1"
                },
                {
                    "id": "section_1_text_137",
                    "type": "paragraph",
                    "text": "Effective date and future review ",
                    "citation_path": "s. 1"
                },
                {
                    "id": "section_1_text_138",
                    "type": "paragraph",
                    "text": "This Guidance became effective on January 1, 2023 and will be reviewed no later than January 1, 2025. ",
                    "citation_path": "s. 1"
                },
                {
                    "id": "section_1_text_139",
                    "type": "paragraph",
                    "text": "About this Guidance  ",
                    "citation_path": "s. 1"
                },
                {
                    "id": "section_1_text_140",
                    "type": "paragraph",
                    "text": "This Guidance is consistent with FSRA’s Guidance Framework . As Interpretation guidance, it ",
                    "citation_path": "s. 1"
                },
                {
                    "id": "section_1_text_141",
                    "type": "paragraph",
                    "text": "describes FSRA’s view of requirements under its legislative mandate (i.e. legislation, regulations and rules) so that non-compliance can lead to enforcement or supervisory action. ",
                    "citation_path": "s. 1"
                },
                {
                    "id": "section_1_text_142",
                    "type": "paragraph",
                    "text": "9 Guidance  ",
                    "citation_path": "s. 1"
                },
                {
                    "id": "section_1_text_143",
                    "type": "paragraph",
                    "text": "GUI APP AU013 6APP | 12.12 .22 ",
                    "citation_path": "s. 1"
                },
                {
                    "id": "section_1_text_144",
                    "type": "paragraph",
                    "text": "As Approach guidance, it also describes FSRA’s internal principles, processes and practices for ",
                    "citation_path": "s. 1"
                },
                {
                    "id": "section_1_text_145",
                    "type": "paragraph",
                    "text": "supervisory action and application of Chief Executive Officer discretion. Approach Guidance may refer to compliance obligations but does not in and of itself create a compliance obligation. ",
                    "citation_path": "s. 1"
                },
                {
                    "id": "section_1_text_146",
                    "type": "paragraph",
                    "text": "Effective Date:  January 1, 2023 ",
                    "citation_path": "s. 1"
                },
                {
                    "id": "section_1_text_147",
                    "type": "paragraph",
                    "text": "[1]Both the CEO of FSRA and FSRA may exercise regulatory authority under the Insurance Act  and Automobil e",
                    "citation_path": "s. 1"
                },
                {
                    "id": "section_1_text_148",
                    "type": "paragraph",
                    "text": "I",
                    "citation_path": "s. 1"
                },
                {
                    "id": "section_1_text_149",
                    "type": "paragraph",
                    "text": "nsurance Rate Stabilization Act . However, for the purposes of this Guidance, reference will only be made to FSRA",
                    "citation_path": "s. 1"
                },
                {
                    "id": "section_1_text_150",
                    "type": "paragraph",
                    "text": "as the CEO may delegate authority to FSRA staff, as permitted by s. 10(2.3) of the Financial Services Regulatory",
                    "citation_path": "s. 1"
                },
                {
                    "id": "section_1_text_151",
                    "type": "paragraph",
                    "text": "Authority of Ontario Act .",
                    "citation_path": "s. 1"
                },
                {
                    "id": "section_1_text_152",
                    "type": "paragraph",
                    "text": "[2]Exclu des fleet rated automobile insurance.",
                    "citation_path": "s. 1"
                },
                {
                    "id": "section_1_text_153",
                    "type": "paragraph",
                    "text": "[3]Fair Treatment of Customers in Insurance",
                    "citation_path": "s. 1"
                },
                {
                    "id": "section_1_text_154",
                    "type": "paragraph",
                    "text": "[4]Insurers are prohibited from charging a rate other than the authorized rate for the PPA category of automobil e",
                    "citation_path": "s. 1"
                },
                {
                    "id": "section_1_text_155",
                    "type": "paragraph",
                    "text": "i",
                    "citation_path": "s. 1"
                },
                {
                    "id": "section_1_text_156",
                    "type": "paragraph",
                    "text": "nsurance by s. 8 of AIRSA. For other than PPA categories, s. 417(1) and s. 417(2) of the Act prohibit an insurer",
                    "citation_path": "s. 1"
                },
                {
                    "id": "section_1_text_157",
                    "type": "paragraph",
                    "text": "from using a risk classification system or rate unless such a risk classification system or rate is approved by FSRA",
                    "citation_path": "s. 1"
                },
                {
                    "id": "section_1_text_158",
                    "type": "paragraph",
                    "text": "or Financial Services Tribunal, authorized under s. 413 or required under the regulations.",
                    "citation_path": "s. 1"
                },
                {
                    "id": "section_1_text_159",
                    "type": "paragraph",
                    "text": "[5]S. 238(1) of the Act prohibits, with respect to automobile insurance, an insurer from declining to issue, terminati ng",
                    "citation_path": "s. 1"
                },
                {
                    "id": "section_1_text_160",
                    "type": "paragraph",
                    "text": "or",
                    "citation_path": "s. 1"
                },
                {
                    "id": "section_1_text_161",
                    "type": "paragraph",
                    "text": " refusing to renew a contract or refusing to provide or continue a coverage endorsement except on a ground fil ed",
                    "citation_path": "s. 1"
                },
                {
                    "id": "section_1_text_162",
                    "type": "paragraph",
                    "text": "w",
                    "citation_path": "s. 1"
                },
                {
                    "id": "section_1_text_163",
                    "type": "paragraph",
                    "text": "ith FSRA.",
                    "citation_path": "s. 1"
                },
                {
                    "id": "section_1_text_164",
                    "type": "paragraph",
                    "text": "[6]Prior to April 1, 2022, FSRA’s stated interpretation of what amounts to declining to issue or refusing to renew a",
                    "citation_path": "s. 1"
                },
                {
                    "id": "section_1_text_165",
                    "type": "paragraph",
                    "text": "c",
                    "citation_path": "s. 1"
                },
                {
                    "id": "section_1_text_166",
                    "type": "paragraph",
                    "text": "ontract is provided for in Interpretation of Sections 237 & 238 of the Insurance Act  and Sections 1(1) and 2(1)(5) t o",
                    "citation_path": "s. 1"
                },
                {
                    "id": "section_1_text_167",
                    "type": "paragraph",
                    "text": "2(",
                    "citation_path": "s. 1"
                },
                {
                    "id": "section_1_text_168",
                    "type": "paragraph",
                    "text": "1)(8) of Regulation 7/00 Unfair or Deceptive Acts or Practices  and Approach to Supervision [Take All Comers",
                    "citation_path": "s. 1"
                },
                {
                    "id": "section_1_text_169",
                    "type": "paragraph",
                    "text": "Rule]. After April 1, 2022, the aforementioned interpretation is expressly reinforced by the Unfair or Deceptive Acts",
                    "citation_path": "s. 1"
                },
                {
                    "id": "section_1_text_170",
                    "type": "paragraph",
                    "text": "or Practices Rule, which in s. 9(1)(i) prescribes as an unfair or deceptive act or practice any conduct, includi ng",
                    "citation_path": "s. 1"
                },
                {
                    "id": "section_1_text_171",
                    "type": "paragraph",
                    "text": "i",
                    "citation_path": "s. 1"
                },
                {
                    "id": "section_1_text_172",
                    "type": "paragraph",
                    "text": "naction or omission, which results in or could reasonably be expected to result in unfair treatment by an insurer to a",
                    "citation_path": "s. 1"
                },
                {
                    "id": "section_1_text_173",
                    "type": "paragraph",
                    "text": "c",
                    "citation_path": "s. 1"
                },
                {
                    "id": "section_1_text_174",
                    "type": "paragraph",
                    "text": "onsumer with regard to any matter relating to the issuance of contracts of automobile insurance or renewals of",
                    "citation_path": "s. 1"
                },
                {
                    "id": "section_1_text_175",
                    "type": "paragraph",
                    "text": "existing contracts of automobile insurance, including but not limited to, variance of formal or informal processes a nd",
                    "citation_path": "s. 1"
                },
                {
                    "id": "section_1_text_176",
                    "type": "paragraph",
                    "text": "pr",
                    "citation_path": "s. 1"
                },
                {
                    "id": "section_1_text_177",
                    "type": "paragraph",
                    "text": "ocedures which make it more difficult for certain persons to interact with an insurer for the purpose of discouragin g",
                    "citation_path": "s. 1"
                },
                {
                    "id": "section_1_text_178",
                    "type": "paragraph",
                    "text": "or",
                    "citation_path": "s. 1"
                },
                {
                    "id": "section_1_text_179",
                    "type": "paragraph",
                    "text": " delaying such persons from applying for, renewing or obtaining automobile insurance.",
                    "citation_path": "s. 1"
                },
                {
                    "id": "section_1_text_180",
                    "type": "paragraph",
                    "text": "[7]S. 238(1) of the Act currently prohibits an insurer from declining to issue, terminating or refusing to renew a",
                    "citation_path": "s. 1"
                },
                {
                    "id": "section_1_text_181",
                    "type": "paragraph",
                    "text": "c",
                    "citation_path": "s. 1"
                },
                {
                    "id": "section_1_text_182",
                    "type": "paragraph",
                    "text": "ontract or refusing to provide or continue a coverage or endorsement, except on a filed ground. S. 238(1) of the Act",
                    "citation_path": "s. 1"
                },
                {
                    "id": "section_1_text_183",
                    "type": "paragraph",
                    "text": "provides a sufficient legal basis for the inclusion of this portion of the underwriting error definition into the Guidance.",
                    "citation_path": "s. 1"
                },
                {
                    "id": "section_1_text_184",
                    "type": "paragraph",
                    "text": "[8]For a breach of AIRSA, FSRA may impose administrative monetary penalties pursuant to s. 11.2(1) -(2), s.",
                    "citation_path": "s. 1"
                },
                {
                    "id": "section_1_text_185",
                    "type": "paragraph",
                    "text": "11.3(1) -(2), s. 11.4(1) -(2), s. 11.5(1) -(2) and s. 11.6. of AIRSA; or lay charges for an offence pursuant to paragraphs",
                    "citation_path": "s. 1"
                },
                {
                    "id": "section_1_text_186",
                    "type": "paragraph",
                    "text": " 10 Guidance  ",
                    "citation_path": "s. 1"
                },
                {
                    "id": "section_1_text_187",
                    "type": "paragraph",
                    "text": "GUI APP AU013 6APP | 12.12 .22 ",
                    "citation_path": "s. 1"
                },
                {
                    "id": "section_1_text_188",
                    "type": "paragraph",
                    "text": "(1)-(3) of s. 12(1) of AIRSA. For a breach of the Act, FSRA may impose administrative monetary penalties pursuant ",
                    "citation_path": "s. 1"
                },
                {
                    "id": "section_1_text_189",
                    "type": "paragraph",
                    "text": "to s. 441.2(1)-(2), s 441.3(1)-(8), s. 441.4(1)-(7), s. 441.5(1)-(2) and s. 441.6(1)-(3) of the Act; or lay charges against ",
                    "citation_path": "s. 1"
                },
                {
                    "id": "section_1_text_190",
                    "type": "paragraph",
                    "text": "an insurer for an offence pursuant to s. 447(2)(a)-(e) of the Act. ",
                    "citation_path": "s. 1"
                },
                {
                    "id": "section_1_text_191",
                    "type": "paragraph",
                    "text": "[9] For a breach of AIRSA, see s. 11(1). For a breach of the Act, see s. 441(2)(b). ",
                    "citation_path": "s. 1"
                },
                {
                    "id": "section_1_text_192",
                    "type": "paragraph",
                    "text": "[10] Rate Regulation Principles ",
                    "citation_path": "s. 1"
                },
                {
                    "id": "section_1_text_193",
                    "type": "paragraph",
                    "text": "[11] FSRA Objects (see section 3) ",
                    "citation_path": "s. 1"
                },
                {
                    "id": "section_1_text_194",
                    "type": "paragraph",
                    "text": "[12] Based on the latest full year data reported to GISA. ",
                    "citation_path": "s. 1"
                },
                {
                    "id": "section_1_text_195",
                    "type": "paragraph",
                    "text": "[13] Threshold is based on the written premiums or written exposures for the specific category of automobile ",
                    "citation_path": "s. 1"
                },
                {
                    "id": "section_1_text_196",
                    "type": "paragraph",
                    "text": "insurance affected by the error. ",
                    "citation_path": "s. 1"
                },
                {
                    "id": "section_1_text_197",
                    "type": "paragraph",
                    "text": "[14] Based on the latest full year data reported to GISA. ",
                    "citation_path": "s. 1"
                },
                {
                    "id": "section_1_text_198",
                    "type": "paragraph",
                    "text": "[15] Threshold is based on the written premiums or written exposures for the specific category of automobile ",
                    "citation_path": "s. 1"
                },
                {
                    "id": "section_1_text_199",
                    "type": "paragraph",
                    "text": "insurance affected by the error.  ",
                    "citation_path": "s. 1"
                },
                {
                    "id": "section_1_text_200",
                    "type": "paragraph",
                    "text": "[16] A remediation plan must be included at the time of reporting.  ",
                    "citation_path": "s. 1"
                },
                {
                    "id": "section_1_text_201",
                    "type": "paragraph",
                    "text": "[17] If an insured has been incorrectly classified under a risk classification system used by an insurer, then s. 2(1) of ",
                    "citation_path": "s. 1"
                },
                {
                    "id": "section_1_text_202",
                    "type": "paragraph",
                    "text": "O. Reg. 777/93: Statutory Conditions - Automobile Insurance (the “Statutory Conditions”) requires an insurer to ",
                    "citation_path": "s. 1"
                },
                {
                    "id": "section_1_text_203",
                    "type": "paragraph",
                    "text": "make any required corrections. ",
                    "citation_path": "s. 1"
                },
                {
                    "id": "section_1_text_204",
                    "type": "section",
                    "text": "If a correction made pursuant to s. 2(1) of the Statutory Conditions results in an insured’s premium being lowered, then the insurer is required by s. 2(2) of the Statutory Conditions to refund the amount of any premium overpayment together with the interest thereon for the period that the incorrect risk classification was in effect. ",
                    "citation_path": "s. 1"
                },
                {
                    "id": "section_1_text_205",
                    "type": "paragraph",
                    "text": "If such a correction is made within the first sixty days a policy is in force and results in an insured’s premium being increased, then pursuant to s. 2(4) of the Statutory Conditions the insurer may require the insured to pay the additional premium without interest.",
                    "citation_path": "s. 1"
                },
                {
                    "id": "section_1_text_206",
                    "type": "paragraph",
                    "text": "[18] Remediation plans should include details of the insurer’s communication plan for consumers affected by the ",
                    "citation_path": "s. 1"
                },
                {
                    "id": "section_1_text_207",
                    "type": "paragraph",
                    "text": "error, as well as the protocol to deal with potential consumer complaints.  ",
                    "citation_path": "s. 1"
                },
                {
                    "id": "section_1_text_208",
                    "type": "paragraph",
                    "text": "[19] Part XIX of the Act provides FSRA with examination and enforcement powers.  ",
                    "citation_path": "s. 1"
                }
            ]
        }
    ]
}